Ailie_Net/__init__.py
Ailie_Net/activations.py
Ailie_Net/layer.py
Ailie_Net/network.py
Ailie_Net/utils.py
ailie_net-0.1.dist-info/LICENSE
ailie_net-0.1.dist-info/METADATA
ailie_net-0.1.dist-info/WHEEL
ailie_net-0.1.dist-info/top_level.txt
ailie_net-0.1.dist-info/RECORD
