Metadata-Version: 2.1
Name: ailie_net
Version: 0.1
Home-page: https://github.com/RyanB-Micro/Ailie_Net
Author: Ryan Brown
License: MIT
License-File: LICENSE
